stan/__init__.py
stan/common.py
stan/fit.py
stan/model.py
stan/plugins.py
pystan-3.9.0.dist-info/LICENSE
pystan-3.9.0.dist-info/METADATA
pystan-3.9.0.dist-info/WHEEL
pystan-3.9.0.dist-info/RECORD
