Metadata-Version: 2.1
Name: pystan
Version: 3.9.0
Summary: Python interface to Stan, a package for Bayesian inference
Home-page: https://mc-stan.org
License: ISC
Author: Allen Riddell
Author-email: riddella@indiana.edu
Requires-Python: >=3.9,<4.0
Classifier: Intended Audience :: Science/Research
Classifier: License :: OSI Approved
Classifier: License :: OSI Approved :: ISC License (ISCL)
Classifier: Programming Language :: Python :: 3
Classifier: Programming Language :: Python :: 3.9
Classifier: Programming Language :: Python :: 3.10
Classifier: Programming Language :: Python :: 3.11
Classifier: Programming Language :: Python :: 3.12
Requires-Dist: aiohttp (>=3.6,<4.0)
Requires-Dist: clikit (>=0.6,<0.7)
Requires-Dist: httpstan (>=4.12,<4.13)
Requires-Dist: numpy (>=1.19,<2.0)
Requires-Dist: pysimdjson (>=5.0.2,<6.0.0)
Requires-Dist: setuptools
Project-URL: Documentation, https://pystan.readthedocs.io
Project-URL: Repository, https://github.com/stan-dev/pystan
